{"id": "76dd33bd-39e7-446f-912b-b9bc9dfc87f3", "filename": "stego_decrypt_demo.png", "file_path": "C:\\Users\\KICHU\\OneDrive\\Desktop\\StegDefenderpro\\web\\uploads\\76dd33bd-39e7-446f-912b-b9bc9dfc87f3.png", "results": {"filename": "76dd33bd-39e7-446f-912b-b9bc9dfc87f3.png", "depth": 0, "info": {"type": "png", "mime": "image/png", "extension": "png"}, "findings": {"verdict": "Stego Detected", "details": [{"message": "Metadata extraction failed: broken PNG file (chunk b'END\\xae')", "severity": "warning"}, {"message": "Detected 172 bytes of data after PNG IEND chunk", "severity": "danger"}, {"message": "Extracted artifact: extracted_png_eof.bin (unknown)", "severity": "warning"}, {"message": "Error analyzing LSB: broken PNG file (chunk b'END\\xae')", "severity": "warning"}, {"message": "Global Intel: SHA256: c45ca5949d816be2748930466af6e65b493429a042e098ef9755a75e352e23f3 (Clean or unknown)", "severity": "info"}], "artifacts": [{"name": "extracted_png_eof.bin", "path": "C:\\Users\\KICHU\\OneDrive\\Desktop\\StegDefenderpro\\stegdefender\\extracted_data\\1773671106\\extracted_png_eof.bin", "type": "unknown", "size": 172, "url": "/extracted/1773671106/extracted_png_eof.bin"}], "metadata": {"Format": "PNG", "Mode": "RGBA", "Size": "1x1", "Format Info": "Portable network graphics"}}, "telemetry": {"entropy_map": [{"offset": 0, "entropy": 3.9522}, {"offset": 64, "entropy": 4.1206}, {"offset": 128, "entropy": 3.8538}, {"offset": 192, "entropy": 3.8956}]}, "nested": [{"relation": "extracted_from_parent", "artifact_name": "extracted_png_eof.bin", "analysis": {"filename": "extracted_png_eof.bin", "depth": 1, "info": {"type": "bin", "mime": "application/octet-stream", "extension": "bin"}, "findings": {"verdict": "Clean", "details": [{"message": "File Entropy: 3.9521", "severity": "info"}, {"message": "Global Intel: SHA256: ab6376dc90a9c7c24a2b1b3b02824a948db75e5a4b3f0aad6e393f4360ee3a3f (Clean or unknown)", "severity": "info"}], "artifacts": [], "metadata": {"Size": "172 bytes", "Type": "Generic/Unknown"}}, "telemetry": {"entropy_map": [{"offset": 0, "entropy": 3.8254}, {"offset": 64, "entropy": 3.8184}, {"offset": 128, "entropy": 3.8654}]}, "nested": [], "url": "/extracted/1773671106/extracted_png_eof.bin"}}]}, "risk_score": 90, "timestamp": "2026-03-16T19:55:06.891219"}